{
  "project_info": {
    "project_number": "655046320725",
    "firebase_url": "https://climbhard-8ef64.firebaseio.com",
    "project_id": "climbhard-8ef64",
    "storage_bucket": "climbhard-8ef64.appspot.com"
  },
  "client": [
    {
      "client_info": {
        "mobilesdk_app_id": "1:655046320725:android:94f6c614268bf51444eadc",
        "android_client_info": {
          "package_name": "com.climbhard"
        }
      },
      "oauth_client": [
        {
          "client_id": "655046320725-e4far62q10vcujuadcaqqlcb2349dj4a.apps.googleusercontent.com",
          "client_type": 1,
          "android_info": {
            "package_name": "com.climbhard",
            "certificate_hash": "ddf270a8c55ab0cc14eddb9c748070b47480104b"
          }
        },
        {
          "client_id": "655046320725-cfe92mprclk7mlufu5tfk89d8mlnsv2n.apps.googleusercontent.com",
          "client_type": 1,
          "android_info": {
            "package_name": "com.climbhard",
            "certificate_hash": "5e8f16062ea3cd2c4a0d547876baa6f38cabf625"
          }
        },
        {
          "client_id": "655046320725-cu1bvg3104cd8nkios1q04ql741pme15.apps.googleusercontent.com",
          "client_type": 3
        }
      ],
      "api_key": [
        {
          "current_key": "AIzaSyDQqHTUBo-IZCscpj5pD4U_47wq7bMhiXA"
        }
      ],
      "services": {
        "appinvite_service": {
          "other_platform_oauth_client": [
            {
              "client_id": "655046320725-cu1bvg3104cd8nkios1q04ql741pme15.apps.googleusercontent.com",
              "client_type": 3
            }
          ]
        }
      }
    }
  ],
  "configuration_version": "1"
}